pytxtchat/__init__.py
pytxtchat/cli.py
pytxtchat/com.py
pytxtchat/bot/__init__.py
pytxtchat/bot/movie_bot.py
pytxtchat/data/__init__.py
pytxtchat/data/manager.py
pytxtchat/data/movies/movies.parquet
pytxtchat/kafka/__init__.py
pytxtchat/kafka/consumer.py
pytxtchat/kafka/producer.py
pytxtchat/textual/__init__.py
pytxtchat/textual/chat.py
pytxtchat/textual/chat.tcss
pytxtchat/textual/stopwatch.py
pytxtchat/textual/stopwatch.tcss
pytxtchat/textual/weather.py
pytxtchat/textual/weather.tcss
pytxtchat-0.5.0.dist-info/METADATA
pytxtchat-0.5.0.dist-info/WHEEL
pytxtchat-0.5.0.dist-info/entry_points.txt
pytxtchat-0.5.0.dist-info/top_level.txt
pytxtchat-0.5.0.dist-info/RECORD
