Metadata-Version: 2.1
Name: pytxtchat
Version: 0.5.0
Summary: Python Terminal Chat Using Apache Kafka
Author-email: dMario24 <data.mario24@gmail.com>
License: GNU
Project-URL: Homepage, https://github.com/dMario24/pytxtchat
Project-URL: Issues, https://github.com/dMario24/pytxtchat/issues
Requires-Python: >=3.9
Requires-Dist: textual>=0.77.0
Requires-Dist: textual-dev>=1.5.1
Requires-Dist: kafka-python>=2.0.2
Requires-Dist: httpx>=0.27.0
Requires-Dist: typer>=0.12.5
Requires-Dist: pandas>=2.2.2
Requires-Dist: pyarrow>=17.0.0
Requires-Dist: termplotlib>=0.3.9
Requires-Dist: tabulate>=0.9.0
Requires-Dist: seaborn>=0.13.2
Requires-Dist: matplotlib>=3.9.2
